.gitignore
LICENSE
MANIFEST.in
README.md
changelog.txt
config.cfg
requirements.txt
setup.py
start.sh
wsgi.py
hass_wh_triggers/__init__.py
hass_wh_triggers/app.py
hass_wh_triggers/config.py
hass_wh_triggers/db.py
hass_wh_triggers/models.py
hass_wh_triggers/util.py
hass_wh_triggers.egg-info/PKG-INFO
hass_wh_triggers.egg-info/SOURCES.txt
hass_wh_triggers.egg-info/dependency_links.txt
hass_wh_triggers.egg-info/requires.txt
hass_wh_triggers.egg-info/top_level.txt
hass_wh_triggers/fido2/__init__.py
hass_wh_triggers/fido2/_tpm.py
hass_wh_triggers/fido2/attestation.py
hass_wh_triggers/fido2/cbor.py
hass_wh_triggers/fido2/client.py
hass_wh_triggers/fido2/cose.py
hass_wh_triggers/fido2/ctap.py
hass_wh_triggers/fido2/ctap1.py
hass_wh_triggers/fido2/ctap2.py
hass_wh_triggers/fido2/extensions.py
hass_wh_triggers/fido2/hid.py
hass_wh_triggers/fido2/nfc.py
hass_wh_triggers/fido2/pcsc.py
hass_wh_triggers/fido2/public_suffix_list.dat
hass_wh_triggers/fido2/rpid.py
hass_wh_triggers/fido2/server.py
hass_wh_triggers/fido2/utils.py
hass_wh_triggers/fido2/webauthn.py
hass_wh_triggers/fido2/win_api.py
hass_wh_triggers/fido2/_pyu2f/__init__.py
hass_wh_triggers/fido2/_pyu2f/base.py
hass_wh_triggers/fido2/_pyu2f/freebsd.py
hass_wh_triggers/fido2/_pyu2f/hidtransport.py
hass_wh_triggers/fido2/_pyu2f/linux.py
hass_wh_triggers/fido2/_pyu2f/macos.py
hass_wh_triggers/fido2/_pyu2f/openbsd.py
hass_wh_triggers/fido2/_pyu2f/windows.py
hass_wh_triggers/static/css/base.css
hass_wh_triggers/static/css/cosmo.bulmaswatch.min.css
hass_wh_triggers/static/images/android-icon-144x144.png
hass_wh_triggers/static/images/android-icon-192x192.png
hass_wh_triggers/static/images/android-icon-36x36.png
hass_wh_triggers/static/images/android-icon-48x48.png
hass_wh_triggers/static/images/android-icon-512x512.png
hass_wh_triggers/static/images/android-icon-72x72.png
hass_wh_triggers/static/images/android-icon-96x96.png
hass_wh_triggers/static/images/apple-icon-114x114.png
hass_wh_triggers/static/images/apple-icon-120x120.png
hass_wh_triggers/static/images/apple-icon-144x144.png
hass_wh_triggers/static/images/apple-icon-152x152.png
hass_wh_triggers/static/images/apple-icon-180x180.png
