Metadata-Version: 1.1
Name: hass-wh-triggers
Version: 0.0.7
Summary: HASS-WH-Triggers
Home-page: https://github.com/danielperna84/hass-wh-triggers
Author: Daniel Perna
Author-email: danielperna84@gmail.com
License: MIT
Keywords: Home Assistant FIDO2 WebAuthn TOTP
Platform: UNKNOWN
Classifier: Programming Language :: Python :: 3.7
